bybit_p2p/__init__.py
bybit_p2p/_exceptions.py
bybit_p2p/_p2p_helper.py
bybit_p2p/_p2p_manager.py
bybit_p2p/_p2p_method.py
bybit_p2p/p2p.py
bybit_p2p/p2p_requests.py
bybit_p2p-1.2.0.dist-info/METADATA
bybit_p2p-1.2.0.dist-info/WHEEL
bybit_p2p-1.2.0.dist-info/licenses/LICENSE
bybit_p2p-1.2.0.dist-info/RECORD
