Metadata-Version: 2.4
Name: bybit_p2p
Version: 1.2.0
Summary: Official Bybit P2P API integration library written in Python.
Project-URL: Homepage, https://github.com/bybit-exchange/bybit_p2p
Project-URL: Issues, https://github.com/bybit-exchange/bybit_p2p/issues
Author-email: Nickolay Kushnarenko <kolya@nk.ax>
License-Expression: MIT
License-File: LICENSE
Classifier: Operating System :: OS Independent
Classifier: Programming Language :: Python :: 3
Requires-Python: >=3.10
Requires-Dist: pycryptodome
Requires-Dist: requests
Requires-Dist: requests-toolbelt
